kivy_reloader/__init__.py
kivy_reloader/android_app.py
kivy_reloader/app.py
kivy_reloader/base_app.py
kivy_reloader/bootstrap.py
kivy_reloader/buildozer.spec
kivy_reloader/compile_app.py
kivy_reloader/config.py
kivy_reloader/delta_transfer.py
kivy_reloader/desktop_app.py
kivy_reloader/kivy-reloader.toml
kivy_reloader/lang.py
kivy_reloader/send_app_to_phone.py
kivy_reloader/tree_formatter.py
kivy_reloader/utils.py
kivy_reloader/configurator/__init__.py
kivy_reloader/configurator/app.py
kivy_reloader/configurator/config_loader.py
kivy_reloader/configurator/gui.py
kivy_reloader/configurator/model.py
kivy_reloader/configurator/schema.py
kivy_reloader/configurator/styles.py
kivy_reloader/configurator/graphics/__init__.py
kivy_reloader/configurator/graphics/gradients.py
kivy_reloader/configurator/screens/core.kv
kivy_reloader/configurator/screens/core.py
kivy_reloader/configurator/theme/__init__.py
kivy_reloader/configurator/theme/colors.py
kivy_reloader/configurator/theme/fonts.py
kivy_reloader/configurator/theme/icons.py
kivy_reloader/configurator/theme/assets/mdi-subset.ttf
kivy_reloader/configurator/theme/assets/twemoji-subset.ttf
kivy_reloader/configurator/widgets/cards/__init__.py
kivy_reloader/configurator/widgets/cards/advanced_card.kv
kivy_reloader/configurator/widgets/cards/advanced_card.py
kivy_reloader/configurator/widgets/cards/audio_card.kv
kivy_reloader/configurator/widgets/cards/audio_card.py
kivy_reloader/configurator/widgets/cards/core_card.kv
kivy_reloader/configurator/widgets/cards/core_card.py
kivy_reloader/configurator/widgets/cards/deployment_card.kv
kivy_reloader/configurator/widgets/cards/deployment_card.py
kivy_reloader/configurator/widgets/cards/device_card.kv
kivy_reloader/configurator/widgets/cards/device_card.py
kivy_reloader/configurator/widgets/cards/display_card.kv
kivy_reloader/configurator/widgets/cards/display_card.py
kivy_reloader/configurator/widgets/cards/notifications_card.kv
kivy_reloader-0.8.3.dist-info/METADATA
kivy_reloader-0.8.3.dist-info/WHEEL
kivy_reloader-0.8.3.dist-info/entry_points.txt
kivy_reloader-0.8.3.dist-info/licenses/LICENSE
kivy_reloader-0.8.3.dist-info/RECORD
