Metadata-Version: 2.4
Name: kivy-reloader
Version: 0.8.3
Summary: Hot reload your Kivy app on multiple Android phones and computer in real-time.
Project-URL: Homepage, https://kivyschool.com/kivy-reloader/
Project-URL: Repository, https://github.com/kivy-school/kivy-reloader
Author-email: filipemarch <filipe.marchesini@gmail.com>
License-File: LICENSE
Requires-Python: >=3.10
Requires-Dist: buildozer>=1.5.0
Requires-Dist: colorama>=0.4.6
Requires-Dist: cython>=3.1.2
Requires-Dist: kaki>=0.1.9
Requires-Dist: pip>=25.1.1
Requires-Dist: plyer>=2.1.0
Requires-Dist: psutil>=7.0.0; sys_platform == 'win32' or sys_platform == 'darwin' or sys_platform == 'linux'
Requires-Dist: readchar>=4.2.1
Requires-Dist: tomlkit>=0.13.3
Requires-Dist: trio>=0.30.0
Requires-Dist: typer>=0.16.0
